ssmdevices/__init__.py
ssmdevices/_version.py
ssmdevices/py.typed
ssmdevices/electronics/__init__.py
ssmdevices/electronics/gps.py
ssmdevices/electronics/mobile.py
ssmdevices/electronics/usb.py
ssmdevices/etc/__init__.py
ssmdevices/etc/instruments/networking/CobhamTM500/setup.txt
ssmdevices/etc/instruments/networking/CobhamTM500/start.txt
ssmdevices/etc/instruments/networking/CobhamTM500/stop.txt
ssmdevices/instruments/__init__.py
ssmdevices/instruments/_minicircuits_usb.py
ssmdevices/instruments/attenuators.py
ssmdevices/instruments/base_station_emulators.py
ssmdevices/instruments/gps_simulator.py
ssmdevices/instruments/motors.py
ssmdevices/instruments/network_analyzers.py
ssmdevices/instruments/networking.py
ssmdevices/instruments/oscilloscopes.py
ssmdevices/instruments/power_sensors.py
ssmdevices/instruments/power_supplies.py
ssmdevices/instruments/signal_analyzers.py
ssmdevices/instruments/signal_generators.py
ssmdevices/instruments/switches.py
ssmdevices/lib/__init__.py
ssmdevices/lib/android-arm64/iperf/iperf
ssmdevices/lib/cal/MiniCircuitsRCDAT_11604210008.csv.xz
ssmdevices/lib/cal/MiniCircuitsRCDAT_11604210014.csv.xz
ssmdevices/lib/cal/MiniCircuitsRCDAT_11604210023.csv.xz
ssmdevices/lib/cal/MiniCircuitsRCDAT_11707090013.csv.xz
ssmdevices/lib/cal/MiniCircuitsRCDAT_11709280051.csv.xz
ssmdevices/lib/cal/MiniCircuitsRCDAT_11803280025.csv.xz
ssmdevices/lib/cal/MiniCircuitsRCDAT_11805010072.csv.xz
ssmdevices/lib/cal/MiniCircuitsRCDAT_11808210006.csv.xz
ssmdevices/lib/cal/MiniCircuitsRCDAT_11812050002.csv.xz
ssmdevices/lib/cal/MiniCircuitsRCDAT_11812050021.csv.xz
ssmdevices/lib/cal/MiniCircuitsRCDAT_11812050022.csv.xz
ssmdevices/lib/cal/MiniCircuitsRCDAT_default.csv.xz
ssmdevices/lib/darwin-arm64/iperf/iperf
ssmdevices/lib/darwin-arm64/iperf3/iperf3
ssmdevices/lib/windows-amd64/adb/AdbWinApi.dll
ssmdevices/lib/windows-amd64/adb/AdbWinUsbApi.dll
ssmdevices/lib/windows-amd64/adb/adb.exe
ssmdevices/lib/windows-amd64/adb/cygwin1.dll
ssmdevices-0.32.0.dist-info/METADATA
ssmdevices-0.32.0.dist-info/WHEEL
ssmdevices-0.32.0.dist-info/licenses/LICENSE.md
ssmdevices-0.32.0.dist-info/RECORD
