Metadata-Version: 2.4
Name: ssmdevices
Version: 0.32.0
Summary: a collection of lab automation drivers implemented with labbench
Project-URL: homepage, https://github.com/usnistgov/ssmdevices
Project-URL: repository, https://github.com/usnistgov/ssmdevices
Project-URL: documentation, https://pages.nist.gov/ssmdevices
Author: Paul Blanchard, Alex Curtin, Ryan Jacobs, Andre Rosete, Audrey Puls, Michael Voecks
Author-email: Dan Kuester <daniel.kuester@nist.gov>, Keith Forsyth <keith.forsyth@nist.gov>, Jordan Bernhardt <jordan.bernhardt@nist.gov>, Duncan McGillivray <duncan.a.mcgillivray@nist.gov>, Yao Ma <yao.ma@nist.gov>, John Ladbury <john.ladbury@nist.gov>
Maintainer-email: Dan Kuester <daniel.kuester@nist.gov>
License: # Licensing
License-File: LICENSE.md
Requires-Python: <3.14,>=3.9
Requires-Dist: brainstem>=2.9.26
Requires-Dist: hidapi
Requires-Dist: labbench<1.0,>=0.36.0
Requires-Dist: pywifi
Provides-Extra: dev
Requires-Dist: labbench[dev]; extra == 'dev'
Requires-Dist: twine>=4.0.2; extra == 'dev'
Provides-Extra: doc
Requires-Dist: labbench[doc]; extra == 'doc'
Provides-Extra: scripts
Requires-Dist: ipympl>=0.9.3; extra == 'scripts'
Requires-Dist: matplotlib; extra == 'scripts'
Requires-Dist: seaborn; extra == 'scripts'
Provides-Extra: tek
Requires-Dist: tekhsi>=2.27.2; extra == 'tek'
Requires-Dist: tm-data-types<0.2.0,>=0.1.0; extra == 'tek'
